Single-Cycle/ARM_CPU.v
`timescale 1ns / 1ps

/*
    Group Members: Nikita Eisenhauer and Warren Seto
    Lab Name: ARM LEGv8 CPU Design (Single-Cycle)
*/

module ARM_CPU
(
  input CLOCK,
  input [31:0] INSTRUCTION,
  input [63:0] REG_DATA1,
  input [63:0] REG_DATA2,
  input [63:0] data_memory_out,
  output reg CONTROL_REG2LOC,
  output reg CONTROL_REGWRITE,
  output reg CONTROL_MEMREAD,
  output reg CONTROL_MEMWRITE,
  output reg CONTROL_BRANCH,
  output reg [4:0] READ_REG_1,
  output [4:0] READ_REG_2,
  output reg [4:0] WRITE_REG,
  output [63:0] ALU_Result_Out,
  output [63:0] WRITE_REG_DATA,
  output reg [63:0] PC
);

  reg [4:0] tempRegNum1;
  reg [4:0] tempRegNum2;
  reg [10:0] tempInstruction;

  reg CONTROL_MEM2REG;
  reg CONTROL_ALUSRC;
  reg CONTROL_UNCON_BRANCH;
  reg [1:0] CONTROL_ALU_OP;

  wire tempALUZero;
  wire[3:0] tempALUControl;
  wire[63:0] tempALUInput2;
  wire[63:0] tempImmediate;
  wire [63:0] tempShiftImmediate;

  wire [63:0] nextnextPC;
  reg CONTROL_JUMP;
  wire [63:0] nextPC;
  wire nextPCZero;
  wire [63:0] shiftPC;
  wire shiftPCZero;
  reg tempBranchZero;

  /* Multiplexer for the Program Counter */
  PCMux mux1(nextPC, shiftPC, CONTROL_JUMP, nextnextPC);

  /* Multiplexer before the Register */
  RegisterMux mux2(tempRegNum1, tempRegNum2, CONTROL_REG2LOC, READ_REG_2);

  /* Multiplexer before the ALU */
  ALUMux mux3(REG_DATA2, tempImmediate, CONTROL_ALUSRC, tempALUInput2);

  /* Multiplexer after the Data memory */
  DataMemMux mux4(data_memory_out, ALU_Result_Out, CONTROL_MEM2REG, WRITE_REG_DATA);

  /* Sign Extention Module */
  SignExtend mod1(INSTRUCTION, tempImmediate);

  /* Shift left by two module */
  ShiftLeft2 mod2(tempImmediate, tempShiftImmediate);

  /* ALU Control for the ALU */
  ALU_Control mod3(CONTROL_ALU_OP, tempInstruction, tempALUControl);

  /* ALU Result between the Registers and the Data Memory */
  ALU aluResult(REG_DATA1, tempALUInput2, tempALUControl, ALU_Result_Out, tempALUZero);

  /* An ALU module to calulcate the next sequential PC */
  ALU adderNextPC(PC, 64'h00000004, 4'b0010, nextPC, nextPCZero);

  /* An ALU module to calulcate a shifted PC */
  ALU adderShiftPC(PC, tempShiftImmediate, 4'b0010, shiftPC, shiftPCZero);


  /* Initialize when the CPU is first run */
  initial begin
    PC = 0;
    CONTROL_REG2LOC = 1'bz;
    CONTROL_MEM2REG = 1'bz;
    CONTROL_REGWRITE = 1'bz;
    CONTROL_MEMREAD = 1'bz;
    CONTROL_MEMWRITE = 1'bz;
    CONTROL_ALUSRC = 1'bz;
    CONTROL_BRANCH = 1'b0;
    CONTROL_UNCON_BRANCH = 1'b0;
    tempBranchZero = tempALUZero & CONTROL_BRANCH;
    CONTROL_JUMP = CONTROL_UNCON_BRANCH | tempBranchZero;
  end

  /* Parse and set the CPU's Control bits */
  always @(posedge CLOCK or INSTRUCTION) begin

    // Set the PC to the jumped value
    if (CONTROL_JUMP == 1'b1) begin
      PC = #1 nextnextPC - 4;
    end

    // Parse the incoming instruction for a given PC
    tempInstruction = INSTRUCTION[31:21];
    tempRegNum1 = INSTRUCTION[20:16];
    tempRegNum2 = INSTRUCTION[4:0];
    READ_REG_1 = INSTRUCTION[9:5];
    WRITE_REG = INSTRUCTION[4:0];

    if (INSTRUCTION[31:26] == 6'b000101) begin // Control bits for B
      CONTROL_REG2LOC = 1'b0;
      CONTROL_MEM2REG = 1'b0;
      CONTROL_REGWRITE = 1'b0;
      CONTROL_MEMREAD = 1'b0;
      CONTROL_MEMWRITE = 1'b0;
      CONTROL_ALUSRC = 1'b0;
      CONTROL_ALU_OP = 2'b01;
      CONTROL_BRANCH = 1'b0;
      CONTROL_UNCON_BRANCH = 1'b1;

    end else if (INSTRUCTION[31:24] == 8'b10110100) begin // Control bits for CBZ
      CONTROL_REG2LOC = 1'b0;
      CONTROL_MEM2REG = 1'b0;
      CONTROL_REGWRITE = 1'b0;
      CONTROL_MEMREAD = 1'b0;
      CONTROL_MEMWRITE = 1'b0;
      CONTROL_ALUSRC = 1'b0;
      CONTROL_ALU_OP = 2'b01;
      CONTROL_BRANCH = 1'b1;
      CONTROL_UNCON_BRANCH = 1'b0;

    end else begin // R-Type Control Bits

      CONTROL_BRANCH = 1'b0;
      CONTROL_UNCON_BRANCH = 1'b0;

      case (tempInstruction)
        11'b11111000010 : begin // Control bits for LDUR
          CONTROL_REG2LOC = 1'bx;
          CONTROL_MEM2REG = 1'b1;
          CONTROL_REGWRITE = 1'b1;
          CONTROL_MEMREAD = 1'b1;
          CONTROL_MEMWRITE = 1'b0;
          CONTROL_ALUSRC = 1'b1;
          CONTROL_ALU_OP = 2'b00;
        end

        11'b11111000000 : begin //Control bits for STUR
          // Control Bits
          CONTROL_REG2LOC = 1'b1;
          CONTROL_MEM2REG = 1'bx;
          CONTROL_REGWRITE = 1'b0;
          CONTROL_MEMREAD = 1'b0;
          CONTROL_MEMWRITE = 1'b1;
          CONTROL_ALUSRC = 1'b1;
          CONTROL_ALU_OP = 2'b00;
        end

        11'b10001011000 : begin //Control bits for ADD
          CONTROL_REG2LOC = 1'b0;
          CONTROL_MEM2REG = 1'b0;
          CONTROL_REGWRITE = 1'b1;
          CONTROL_MEMREAD = 1'b0;
          CONTROL_MEMWRITE = 1'b0;
          CONTROL_ALUSRC = 1'b0;
          CONTROL_ALU_OP = 2'b10;
        end

        11'b11001011000 : begin //Control bits for SUB
          CONTROL_REG2LOC = 1'b0;
          CONTROL_MEM2REG = 1'b0;
          CONTROL_REGWRITE = 1'b1;
          CONTROL_MEMREAD = 1'b0;
          CONTROL_MEMWRITE = 1'b0;
          CONTROL_ALUSRC = 1'b0;
          CONTROL_ALU_OP = 2'b10;
        end

        11'b10001010000 : begin //Control bits for AND
          CONTROL_REG2LOC = 1'b0;
          CONTROL_MEM2REG = 1'b0;
          CONTROL_REGWRITE = 1'b1;
          CONTROL_MEMREAD = 1'b0;
          CONTROL_MEMWRITE = 1'b0;
          CONTROL_ALUSRC = 1'b0;
          CONTROL_ALU_OP = 2'b10;
        end

        11'b10101010000 : begin //Control bits for ORR
          CONTROL_REG2LOC = 1'b0;
          CONTROL_MEM2REG = 1'b0;
          CONTROL_REGWRITE = 1'b1;
          CONTROL_MEMREAD = 1'b0;
          CONTROL_MEMWRITE = 1'b0;
          CONTROL_ALUSRC = 1'b0;
          CONTROL_ALU_OP = 2'b10;
        end
      endcase
    end

    //Determine whether to branch
    tempBranchZero = tempALUZero & CONTROL_BRANCH;
    CONTROL_JUMP = CONTROL_UNCON_BRANCH | tempBranchZero;

    // For non-branch code, set the next sequential PC value
    if (CONTROL_JUMP == 1'b0) begin
    	PC <= #1 nextnextPC;
    end
  end
endmodule


module PCMux
(
  input [63:0] pcInput,
  input [63:0] shiftInput,
  input CONTROL_JUMP,
  output reg [63:0] pcOut
);

  always @(pcInput, shiftInput, CONTROL_JUMP, pcOut) begin
    if (CONTROL_JUMP == 0) begin
      pcOut = pcInput;
    end

    else begin
      pcOut = shiftInput;
    end
  end
endmodule


module RegisterMux
(
  input [4:0] input1,
  input [4:0] input2,
  input CONTROL_REG2LOC,
  output reg [4:0] muxOutput
);

  always @(input1, input2, CONTROL_REG2LOC) begin

    if (CONTROL_REG2LOC == 0) begin
      muxOutput = input1;
    end

    else begin
      muxOutput = input2;
    end
  end
endmodule


module ALUMux
(
  input [63:0] input1,
  input [63:0] input2,
  input CONTROL_ALUSRC,
  output reg [63:0] out
);

  always @(input1, input2, CONTROL_ALUSRC, out) begin

    if (CONTROL_ALUSRC == 0) begin
      out = input1;
    end

    else begin
      out = input2;
    end
  end
endmodule


module DataMemMux
(
  input [63:0] readData,
  input [63:0] aluOutput,
  input CONTROL_MEM2REG,
  output reg [63:0] out
);

  always @(readData, aluOutput, CONTROL_MEM2REG, out) begin
    if (CONTROL_MEM2REG == 0) begin
      out = aluOutput;
    end

    else begin
      out = readData;
    end
  end
endmodule


module SignExtend
(
  input [31:0] inputInstruction,
  output reg [63:0] outImmediate
);

    always @(inputInstruction) begin

      if (inputInstruction[31:26] == 6'b000101) begin // B
        outImmediate[25:0] = inputInstruction[25:0];
        outImmediate[63:26] = {64{outImmediate[25]}};

      end else if (inputInstruction[31:24] == 8'b10110100) begin // CBZ
        outImmediate[19:0] = inputInstruction[23:5];
        outImmediate[63:20] = {64{outImmediate[19]}};

      end else begin // D Type
        outImmediate[9:0] = inputInstruction[20:12];
        outImmediate[63:10] = {64{outImmediate[9]}};
      end
    end
endmodule


module ShiftLeft2
(
  input [63:0] inputData,
  output reg [63:0] outputData
);

  always @(inputData) begin
    outputData = inputData << 2;
  end
endmodule


module ALU_Control
(
  input [1:0] ALU_Op,
  input [10:0] ALU_INSTRUCTION,
  output reg [3:0] ALU_Out
);

  always @(ALU_Op or ALU_INSTRUCTION) begin

    case (ALU_Op)
      2'b00 : ALU_Out = 4'b0010;
      2'b01 : ALU_Out = 4'b0111;
      2'b10 : begin

        case (ALU_INSTRUCTION)
          11'b10001011000 : ALU_Out = 4'b0010; // ADD
          11'b11001011000 : ALU_Out = 4'b0110; // SUB
          11'b10001010000 : ALU_Out = 4'b0000; // AND
          11'b10101010000 : ALU_Out = 4'b0001; // ORR
        endcase
      end
    endcase
  end
endmodule


module ALU
(
  input [63:0] A,
  input [63:0] B,
  input [3:0] CONTROL,
  output reg [63:0] RESULT,
  output reg ZEROFLAG
);

  always @(A or B or CONTROL) begin
    case (CONTROL)
      4'b0000 : RESULT = A & B;
      4'b0001 : RESULT = A | B;
      4'b0010 : RESULT = A + B;
      4'b0110 : RESULT = A - B;
      4'b0111 : RESULT = B;
      4'b1100 : RESULT = ~(A | B);
    endcase

    if (RESULT == 0) begin
      ZEROFLAG = 1'b1;
    end else begin
      ZEROFLAG = 1'b0;
    end
  end
endmodule


module Instruction_Memory
(
  input [63:0] PC,
  output reg [31:0] CPU_Instruction
);

  reg [8:0] Data[63:0];

  initial begin

    // ADD x5, x3, x2
    Data[0] = 8'h8B;
    Data[1] = 8'h02;
    Data[2] = 8'h00;
    Data[3] = 8'h65;

    // LDUR x2, [x10]
    Data[4] = 8'hF8;
    Data[5] = 8'h40;
    Data[6] = 8'h01;
    Data[7] = 8'h42;

    // STUR x4, [x7, #1]
    Data[8] = 8'hF8;
    Data[9] = 8'h00;
    Data[10] = 8'h10;
    Data[11] = 8'hE4;

    // CBZ x1, #2
    Data[12] = 8'hB4;
    Data[13] = 8'h00;
    Data[14] = 8'h00;
    Data[15] = 8'h41;

    // LDUR x3, [x10, #1]
    Data[16] = 8'hF8;
    Data[17] = 8'h40;
    Data[18] = 8'h11;
    Data[19] = 8'h43;

    // SUB x4, x3, x2
    Data[20] = 8'hCB;
    Data[21] = 8'h02;
    Data[22] = 8'h00;
    Data[23] = 8'h64;

    // CBZ x0, #2
    Data[24] = 8'hB4;
    Data[25] = 8'h00;
    Data[26] = 8'h00;
    Data[27] = 8'h40;

    // LDUR x2 [x10]
    Data[28] = 8'hF8;
    Data[29] = 8'h40;
    Data[30] = 8'h01;
    Data[31] = 8'h42;

    // ORR x6, x2, x3
    Data[32] = 8'hAA;
    Data[33] = 8'h03;
    Data[34] = 8'h00;
    Data[35] = 8'h46;

    // AND x7, x2, x3
    Data[36] = 8'h8A;
    Data[37] = 8'h03;
    Data[38] = 8'h00;
    Data[39] = 8'h47;


    // B #2
    Data[40] = 8'h14;
    Data[41] = 8'h00;
    Data[42] = 8'h00;
    Data[43] = 8'h03;

    // LDUR x3, [x10, #1]
    Data[44] = 8'hF8;
    Data[45] = 8'h40;
    Data[46] = 8'h11;
    Data[47] = 8'h43;

    // ADD x8, x0, x1
    Data[48] = 8'h8B;
    Data[49] = 8'h01;
    Data[50] = 8'h00;
    Data[51] = 8'h08;
  end

  always @(PC) begin
    CPU_Instruction[8:0] = Data[PC+3];
    CPU_Instruction[16:8] = Data[PC+2];
    CPU_Instruction[24:16] = Data[PC+1];
    CPU_Instruction[31:24] = Data[PC];
  end
endmodule


module Registers
(
  input [4:0] read1,
  input [4:0] read2,
  input [4:0] writeReg,
  input [63:0] writeData,
  input CONTROL_REGWRITE,
  output reg [63:0] data1,
  output reg [63:0] data2
);

  reg [63:0] Data[31:0];

  integer initCount;

  initial begin

    for (initCount = 0; initCount < 31; initCount = initCount + 1) begin
      Data[initCount] = initCount;
    end

    //Data[31] = 64’h00000000;
    Data[31] = 0;
  end

  always @(read1, read2, writeReg, writeData, CONTROL_REGWRITE) begin

    data1 = Data[read1];
    data2 = Data[read2];

    if (CONTROL_REGWRITE == 1) begin
      Data[writeReg] = writeData;
    end
  end
endmodule


module Data_Memory
(
  input [63:0] inputAddress,
  input [63:0] inputData,
  input CONTROL_MemRead,
  input CONTROL_MemWrite,
  output reg [63:0] outputData
);

  reg [63:0] Data[31:0];

  integer initCount;

  initial begin
    for (initCount = 0; initCount < 32; initCount = initCount + 1) begin
      Data[initCount] = initCount * 100;
    end

   Data[10] = 1540;
   Data[11] = 2117;
  end

    always @(inputAddress, inputData, CONTROL_MemRead, CONTROL_MemWrite) begin
      if (CONTROL_MemWrite == 1) begin
        Data[inputAddress] = inputData;
      end

      if (CONTROL_MemRead == 1) begin
        outputData = Data[inputAddress];
      end
    end
endmodule

Single-Cycle/CPU_TEST.v
`timescale 1ns / 1ps

/*
    Group Members: Nikita Eisenhauer and Warren Seto
    Lab Name: ARM LEGv8 CPU Testbench (Single-Cycle)
*/

module CPU_TEST;

  /* Clock Signal */
  reg CLOCK;

  /* Wires to connect instruction memory to CPU */
  wire [63:0] instructionPC;
  wire [31:0] instructionOut;

  /* Wires to connect registers to CPU */
  wire [4:0] READ_REG_1;
  wire [4:0] READ_REG_2;
  wire [4:0] WRITE_REG;
  wire [63:0] WRITE_DATA;
  wire [63:0] DATA_OUT_1;
  wire [63:0] DATA_OUT_2;

  /* Wires to connect Data Memory to CPU */
  wire [63:0] data_memory_out;
  wire [63:0] ALU_Result_Out;

  /* Wires to connect CPU Control Lines to Memories */
  wire CONTROL_REG2LOC;
  wire CONTROL_REGWRITE;
  wire CONTROL_MEMREAD;
  wire CONTROL_MEMWRITE;
  wire CONTROL_BRANCH;

  /* Instruction Memory Module */
  Instruction_Memory mem1
  (
    instructionPC,
    instructionOut
  );

  /* Registers Module */
  Registers mem2
  (
    READ_REG_1,
    READ_REG_2,
    WRITE_REG,
    WRITE_DATA,
    CONTROL_REGWRITE,
    DATA_OUT_1,
    DATA_OUT_2
  );

  /* Data Memory Module */
  Data_Memory mem3
  (
    ALU_Result_Out,
    DATA_OUT_2,
    CONTROL_MEMREAD,
    CONTROL_MEMWRITE,
    data_memory_out
  );

  /* CPU Module */
  ARM_CPU core
  (
    .CLOCK(CLOCK),
    .INSTRUCTION(instructionOut),
    .PC(instructionPC),
    .CONTROL_REG2LOC(CONTROL_REG2LOC),
    .CONTROL_REGWRITE(CONTROL_REGWRITE),
    .CONTROL_MEMREAD(CONTROL_MEMREAD),
    .CONTROL_MEMWRITE(CONTROL_MEMWRITE),
    .CONTROL_BRANCH(CONTROL_BRANCH),
    .READ_REG_1(READ_REG_1),
    .READ_REG_2(READ_REG_2),
    .WRITE_REG(WRITE_REG),
    .REG_DATA1(DATA_OUT_1),
    .REG_DATA2(DATA_OUT_2),
    .ALU_Result_Out(ALU_Result_Out),
    .data_memory_out(data_memory_out),
    .WRITE_REG_DATA(WRITE_DATA)
  );

  /* Setup the clock */
  initial begin
    $dumpfile("waveform.vcd");
    $dumpvars;
    CLOCK = 1'b0;
    #30 $finish;
  end

  /* Toggle the clock */
  always begin
    #1 CLOCK = ~CLOCK;
  end
endmodule

Single-Cycle/waveform.vcd
$date
	Tue Feb 18 21:05:02 2020
$end
$version
	Icarus Verilog
$end
$timescale
	1ps
$end
$scope module CPU_TEST $end
$var wire 64 ! instructionPC [63:0] $end
$var wire 32 " instructionOut [31:0] $end
$var wire 64 # data_memory_out [63:0] $end
$var wire 5 $ WRITE_REG [4:0] $end
$var wire 64 % WRITE_DATA [63:0] $end
$var wire 5 & READ_REG_2 [4:0] $end
$var wire 5 ' READ_REG_1 [4:0] $end
$var wire 64 ( DATA_OUT_2 [63:0] $end
$var wire 64 ) DATA_OUT_1 [63:0] $end
$var wire 1 * CONTROL_REGWRITE $end
$var wire 1 + CONTROL_REG2LOC $end
$var wire 1 , CONTROL_MEMWRITE $end
$var wire 1 - CONTROL_MEMREAD $end
$var wire 1 . CONTROL_BRANCH $end
$var wire 64 / ALU_Result_Out [63:0] $end
$var reg 1 0 CLOCK $end
$scope module core $end
$var wire 1 0 CLOCK $end
$var wire 64 1 tempShiftImmediate [63:0] $end
$var wire 64 2 tempImmediate [63:0] $end
$var wire 1 3 tempALUZero $end
$var wire 64 4 tempALUInput2 [63:0] $end
$var wire 4 5 tempALUControl [3:0] $end
$var wire 1 6 shiftPCZero $end
$var wire 64 7 shiftPC [63:0] $end
$var wire 64 8 nextnextPC [63:0] $end
$var wire 1 9 nextPCZero $end
$var wire 64 : nextPC [63:0] $end
$var wire 64 ; data_memory_out [63:0] $end
$var wire 64 < WRITE_REG_DATA [63:0] $end
$var wire 64 = REG_DATA2 [63:0] $end
$var wire 64 > REG_DATA1 [63:0] $end
$var wire 5 ? READ_REG_2 [4:0] $end
$var wire 32 @ INSTRUCTION [31:0] $end
$var wire 64 A ALU_Result_Out [63:0] $end
$var reg 1 B CONTROL_ALUSRC $end
$var reg 2 C CONTROL_ALU_OP [1:0] $end
$var reg 1 . CONTROL_BRANCH $end
$var reg 1 D CONTROL_JUMP $end
$var reg 1 E CONTROL_MEM2REG $end
$var reg 1 - CONTROL_MEMREAD $end
$var reg 1 , CONTROL_MEMWRITE $end
$var reg 1 + CONTROL_REG2LOC $end
$var reg 1 * CONTROL_REGWRITE $end
$var reg 1 F CONTROL_UNCON_BRANCH $end
$var reg 64 G PC [63:0] $end
$var reg 5 H READ_REG_1 [4:0] $end
$var reg 5 I WRITE_REG [4:0] $end
$var reg 1 J tempBranchZero $end
$var reg 11 K tempInstruction [10:0] $end
$var reg 5 L tempRegNum1 [4:0] $end
$var reg 5 M tempRegNum2 [4:0] $end
$scope module adderNextPC $end
$var wire 64 N A [63:0] $end
$var wire 64 O B [63:0] $end
$var wire 4 P CONTROL [3:0] $end
$var reg 64 Q RESULT [63:0] $end
$var reg 1 9 ZEROFLAG $end
$upscope $end
$scope module adderShiftPC $end
$var wire 64 R A [63:0] $end
$var wire 4 S CONTROL [3:0] $end
$var wire 64 T B [63:0] $end
$var reg 64 U RESULT [63:0] $end
$var reg 1 6 ZEROFLAG $end
$upscope $end
$scope module aluResult $end
$var wire 4 V CONTROL [3:0] $end
$var wire 64 W B [63:0] $end
$var wire 64 X A [63:0] $end
$var reg 64 Y RESULT [63:0] $end
$var reg 1 3 ZEROFLAG $end
$upscope $end
$scope module mod1 $end
$var wire 32 Z inputInstruction [31:0] $end
$var reg 64 [ outImmediate [63:0] $end
$upscope $end
$scope module mod2 $end
$var wire 64 \ inputData [63:0] $end
$var reg 64 ] outputData [63:0] $end
$upscope $end
$scope module mod3 $end
$var wire 11 ^ ALU_INSTRUCTION [10:0] $end
$var wire 2 _ ALU_Op [1:0] $end
$var reg 4 ` ALU_Out [3:0] $end
$upscope $end
$scope module mux1 $end
$var wire 1 D CONTROL_JUMP $end
$var wire 64 a pcInput [63:0] $end
$var wire 64 b shiftInput [63:0] $end
$var reg 64 c pcOut [63:0] $end
$upscope $end
$scope module mux2 $end
$var wire 1 + CONTROL_REG2LOC $end
$var wire 5 d input1 [4:0] $end
$var wire 5 e input2 [4:0] $end
$var reg 5 f muxOutput [4:0] $end
$upscope $end
$scope module mux3 $end
$var wire 1 B CONTROL_ALUSRC $end
$var wire 64 g input2 [63:0] $end
$var wire 64 h input1 [63:0] $end
$var reg 64 i out [63:0] $end
$upscope $end
$scope module mux4 $end
$var wire 1 E CONTROL_MEM2REG $end
$var wire 64 j aluOutput [63:0] $end
$var wire 64 k readData [63:0] $end
$var reg 64 l out [63:0] $end
$upscope $end
$upscope $end
$scope module mem1 $end
$var wire 64 m PC [63:0] $end
$var reg 32 n CPU_Instruction [31:0] $end
$upscope $end
$scope module mem2 $end
$var wire 1 * CONTROL_REGWRITE $end
$var wire 5 o read1 [4:0] $end
$var wire 5 p read2 [4:0] $end
$var wire 64 q writeData [63:0] $end
$var wire 5 r writeReg [4:0] $end
$var reg 64 s data1 [63:0] $end
$var reg 64 t data2 [63:0] $end
$var integer 32 u initCount [31:0] $end
$upscope $end
$scope module mem3 $end
$var wire 1 - CONTROL_MemRead $end
$var wire 1 , CONTROL_MemWrite $end
$var wire 64 v inputAddress [63:0] $end
$var wire 64 w inputData [63:0] $end
$var reg 64 x outputData [63:0] $end
$var integer 32 y initCount [31:0] $end
$upscope $end
$upscope $end
$enddefinitions $end
#0
$dumpvars
b100000 y
bx x
b10 w
b101 v
b11111 u
b10 t
b11 s
b101 r
b101 q
b10 p
b11 o
b10001011000000100000000001100101 n
b0 m
b101 l
bx k
b101 j
b10 i
b10 h
b100000 g
b10 f
b101 e
b10 d
b100 c
b10000000 b
b100 a
b10 `
b10 _
b10001011000 ^
b10000000 ]
b100000 \
b100000 [
b10001011000000100000000001100101 Z
b101 Y
b11 X
b10 W
b10 V
b10000000 U
b10000000 T
b10 S
b0 R
b100 Q
b10 P
b100 O
b0 N
b101 M
b10 L
b10001011000 K
0J
b101 I
b11 H
b0 G
0F
0E
0D
b10 C
0B
b101 A
b10001011000000100000000001100101 @
b10 ?
b11 >
b10 =
b101 <
bx ;
b100 :
09
b100 8
b10000000 7
06
b10 5
b10 4
03
b100000 2
b10000000 1
00
b101 /
0.
0-
0,
0+
1*
b11 )
b10 (
b11 '
b10 &
b101 %
b101 $
bx #
b10001011000000100000000001100101 "
b0 !
$end
#1000
b111110100 (
b111110100 =
b111110100 h
b111110100 t
b111110100 w
b1010 /
b1010 A
b1010 Y
b1010 j
b1010 v
b11000000100 #
b11000000100 ;
b11000000100 k
b11000000100 x
b11000000100 %
b11000000100 <
b11000000100 l
b11000000100 q
b1010 )
b1010 >
b1010 X
b1010 s
b0 1
b0 T
b0 ]
b0 4
b0 W
b0 i
b1000 8
b1000 c
b0 C
b0 _
1B
1-
1E
x+
b10 $
b10 I
b10 r
b1010 '
b1010 H
b1010 o
b10 M
b10 e
b0 L
b0 d
b11111000010 K
b11111000010 ^
b0 2
b0 [
b0 \
b0 g
b1000 :
b1000 Q
b1000 a
b100 7
b100 U
b100 b
b11111000010000000000000101000010 "
b11111000010000000000000101000010 @
b11111000010000000000000101000010 Z
b11111000010000000000000101000010 n
b100 !
b100 G
b100 N
b100 R
b100 m
10
#2000
00
#3000
10
#4000
b1000 /
b1000 A
b1000 Y
b1000 j
b1000 v
b100 (
b100 =
b100 h
b100 t
b100 w
b111 )
b111 >
b111 X
b111 s
b100 &
b100 ?
b100 f
b100 p
b100 1
b100 T
b100 ]
b1 4
b1 W
b1 i
b1100 8
b1100 c
1,
0-
0*
xE
1+
b100 $
b100 I
b100 r
b111 '
b111 H
b111 o
b100 M
b100 e
b11111000000 K
b11111000000 ^
b1 2
b1 [
b1 \
b1 g
b1100 :
b1100 Q
b1100 a
b1100 7
b1100 U
b1100 b
b11111000000000000001000011100100 "
b11111000000000000001000011100100 @
b11111000000000000001000011100100 Z
b11111000000000000001000011100100 n
b1000 !
b1000 G
b1000 N
b1000 R
b1000 m
00
#5000
10
#6000
13
b0 /
b0 A
b0 Y
b0 j
b0 v
b0 %
b0 <
b0 l
b0 q
b0 (
b0 =
b0 h
b0 t
b0 w
b11000000100 )
b11000000100 >
b11000000100 X
b11000000100 s
b0 &
b0 ?
b0 f
b0 p
b111 5
b111 V
b111 `
b1000 1
b1000 T
b1000 ]
b0 4
b0 W
b0 i
b10000 8
b10000 c
1.
b1 C
b1 _
0B
0,
0E
0+
b1 $
b1 I
b1 r
b10 '
b10 H
b10 o
b1 M
b1 e
b10110100000 K
b10110100000 ^
b10 2
b10 [
b10 \
b10 g
b10000 :
b10000 Q
b10000 a
b10100 7
b10100 U
b10100 b
b10110100000000000000000001000001 "
b10110100000000000000000001000001 @
b10110100000000000000000001000001 Z
b10110100000000000000000001000001 n
b1100 !
b1100 G
b1100 N
b1100 R
b1100 m
00
#7000
b10100 8
b10100 c
1D
1J
10
#8000
00
#9000
10
#10000
b100 1
b100 T
b100 ]
b10100 8
b10100 c
b1 2
b1 [
b1 \
b1 g
b10100 :
b10100 Q
b10100 a
b10100 7
b10100 U
b10100 b
b11111000010000000001000101000011 "
b11111000010000000001000101000011 @
b11111000010000000001000101000011 Z
b11111000010000000001000101000011 n
b10000 !
b10000 G
b10000 N
b10000 R
b10000 m
00
#11000
03
b1011 /
b1011 A
b1011 Y
b1011 j
b1011 v
b1 4
b1 W
b1 i
b100001000101 #
b100001000101 ;
b100001000101 k
b100001000101 x
b100001000101 %
b100001000101 <
b100001000101 l
b100001000101 q
b0 (
b0 =
b0 h
b0 t
b0 w
b1010 )
b1010 >
b1010 X
b1010 s
b11 &
b11 ?
b11 f
b11 p
b10 5
b10 V
b10 `
0D
0J
b0 C
b0 _
1B
1-
1*
1E
x+
0.
b11 $
b11 I
b11 r
b1010 '
b1010 H
b1010 o
b11 M
b11 e
b11111000010 K
b11111000010 ^
10
#12000
b1001000001 /
b1001000001 A
b1001000001 Y
b1001000001 j
b1001000001 v
b1001000001 %
b1001000001 <
b1001000001 l
b1001000001 q
b11000000100 (
b11000000100 =
b11000000100 h
b11000000100 t
b11000000100 w
b100001000101 )
b100001000101 >
b100001000101 X
b100001000101 s
b10 &
b10 ?
b10 f
b10 p
b110 5
b110 V
b110 `
b10000000 1
b10000000 T
b10000000 ]
b11000000100 4
b11000000100 W
b11000000100 i
b11000 8
b11000 c
b10 C
b10 _
0B
0-
0E
0+
b100 $
b100 I
b100 r
b11 '
b11 H
b11 o
b100 M
b100 e
b10 L
b10 d
b11001011000 K
b11001011000 ^
b100000 2
b100000 [
b100000 \
b100000 g
b11000 :
b11000 Q
b11000 a
b10010100 7
b10010100 U
b10010100 b
b11001011000000100000000001100100 "
b11001011000000100000000001100100 @
b11001011000000100000000001100100 Z
b11001011000000100000000001100100 n
b10100 !
b10100 G
b10100 N
b10100 R
b10100 m
00
#13000
10
#14000
13
b0 %
b0 <
b0 l
b0 q
b0 4
b0 W
b0 i
b0 /
b0 A
b0 Y
b0 j
b0 v
b0 (
b0 =
b0 h
b0 t
b0 w
b11000000100 )
b11000000100 >
b11000000100 X
b11000000100 s
b0 &
b0 ?
b0 f
b0 p
b111 5
b111 V
b111 `
b1000 1
b1000 T
b1000 ]
b11100 8
b11100 c
1.
b1 C
b1 _
0*
b0 $
b0 I
b0 r
b10 '
b10 H
b10 o
b0 M
b0 e
b0 L
b0 d
b10110100000 K
b10110100000 ^
b10 2
b10 [
b10 \
b10 g
b11100 :
b11100 Q
b11100 a
b100000 7
b100000 U
b100000 b
b10110100000000000000000001000000 "
b10110100000000000000000001000000 @
b10110100000000000000000001000000 Z
b10110100000000000000000001000000 n
b11000 !
b11000 G
b11000 N
b11000 R
b11000 m
00
#15000
b100000 8
b100000 c
1D
1J
10
#16000
00
#17000
10
#18000
b0 1
b0 T
b0 ]
b11100 8
b11100 c
b0 2
b0 [
b0 \
b0 g
b100000 :
b100000 Q
b100000 a
b11100 7
b11100 U
b11100 b
b11111000010000000000000101000010 "
b11111000010000000000000101000010 @
b11111000010000000000000101000010 Z
b11111000010000000000000101000010 n
b11100 !
b11100 G
b11100 N
b11100 R
b11100 m
00
#19000
03
b1010 /
b1010 A
b1010 Y
b1010 j
b1010 v
b100000 8
b100000 c
b100 #
b100 ;
b100 k
b100 x
b100 %
b100 <
b100 l
b100 q
b0 (
b0 =
b0 h
b0 t
b0 w
b1010 )
b1010 >
b1010 X
b1010 s
b10 &
b10 ?
b10 f
b10 p
b10 5
b10 V
b10 `
0D
0J
b0 C
b0 _
1B
1-
1*
1E
x+
0.
b10 $
b10 I
b10 r
b1010 '
b1010 H
b1010 o
b10 M
b10 e
b11111000010 K
b11111000010 ^
10
#20000
00
#21000
10
#22000
b100001000101 4
b100001000101 W
b100001000101 i
b100001000101 /
b100001000101 A
b100001000101 Y
b100001000101 j
b100001000101 v
b100001000101 %
b100001000101 <
b100001000101 l
b100001000101 q
b100001000101 (
b100001000101 =
b100001000101 h
b100001000101 t
b100001000101 w
b100 )
b100 >
b100 X
b100 s
b11 &
b11 ?
b11 f
b11 p
b1 5
b1 V
b1 `
b11000000 1
b11000000 T
b11000000 ]
b100100 8
b100100 c
b10 C
b10 _
0B
0-
0E
0+
b110 $
b110 I
b110 r
b10 '
b10 H
b10 o
b110 M
b110 e
b11 L
b11 d
b10101010000 K
b10101010000 ^
b110000 2
b110000 [
b110000 \
b110000 g
b100100 :
b100100 Q
b100100 a
b11100000 7
b11100000 U
b11100000 b
b10101010000000110000000001000110 "
b10101010000000110000000001000110 @
b10101010000000110000000001000110 Z
b10101010000000110000000001000110 n
b100000 !
b100000 G
b100000 N
b100000 R
b100000 m
00
#23000
10
